odoo/addons/document_validation_dms_field/__init__.py
odoo/addons/document_validation_dms_field/__manifest__.py
odoo/addons/document_validation_dms_field/data/dms_category_data.xml
odoo/addons/document_validation_dms_field/data/dms_storage_data.xml
odoo/addons/document_validation_dms_field/models/__init__.py
odoo/addons/document_validation_dms_field/models/crm_dms_rules.py
odoo/addons/document_validation_dms_field/models/dms_category.py
odoo/addons/document_validation_dms_field/models/dms_directory.py
odoo/addons/document_validation_dms_field/security/ir.model.access.csv
odoo/addons/document_validation_dms_field/views/crm_dms_rules_views.xml
odoo/addons/document_validation_dms_field/views/crm_lead_views.xml
odoo/addons/document_validation_dms_field/views/crm_views.xml
odoo/addons/document_validation_dms_field/views/dms_category_views.xml
odoo/addons/document_validation_dms_field/views/dms_directory_views.xml
odoo/addons/document_validation_dms_field/views/dms_field_views.xml
odoo12_addon_document_validation_dms_field-12.0.0.0.2.dist-info/METADATA
odoo12_addon_document_validation_dms_field-12.0.0.0.2.dist-info/WHEEL
odoo12_addon_document_validation_dms_field-12.0.0.0.2.dist-info/top_level.txt
odoo12_addon_document_validation_dms_field-12.0.0.0.2.dist-info/RECORD
