Metadata-Version: 2.1
Name: odoo12-addon-document-validation-dms-field
Version: 12.0.0.0.2
Summary: document_validation_dms_field
Home-page: UNKNOWN
Author: Som IT, Som Connexió
License: UNKNOWN
Platform: UNKNOWN
Classifier: Programming Language :: Python
Classifier: Framework :: Odoo
Classifier: Framework :: Odoo :: 12.0
Requires-Python: >=3.5
Requires-Dist: odoo12-addon-dms
Requires-Dist: odoo12-addon-dms-field
Requires-Dist: odoo (<12.1dev,>=12.0a)
